talos_config/__init__.py
talos_config/loader.py
talos_config-0.1.0.dist-info/METADATA
talos_config-0.1.0.dist-info/WHEEL
talos_config-0.1.0.dist-info/top_level.txt
talos_config-0.1.0.dist-info/RECORD
