Metadata-Version: 2.4
Name: talos-config
Version: 0.1.0
Summary: Configuration loader for Talos Protocol services
Author: Talos Protocol
Requires-Python: >=3.9
Requires-Dist: talos-contracts
Requires-Dist: pyyaml>=6.0
Requires-Dist: pydantic>=2.0.0
